proto_pixplus_pb2.py
proto_pixplus_pb2-1.0.20.dist-info/LICENSE
proto_pixplus_pb2-1.0.20.dist-info/METADATA
proto_pixplus_pb2-1.0.20.dist-info/WHEEL
proto_pixplus_pb2-1.0.20.dist-info/top_level.txt
proto_pixplus_pb2-1.0.20.dist-info/RECORD
