Metadata-Version: 2.1
Name: proto-pixplus-pb2
Version: 1.0.20
Summary: A package for Pix+ services, which contain proto types
Home-page: https://github.com/pypa/proto_pixplus_pb2
Author: Udini.co
Author-email: bouzguenda.medfiras@gmail.com
Project-URL: Bug Tracker, https://github.com/pypa/proto_pixplus_pb2/issues
Classifier: Programming Language :: Python :: 3
Classifier: License :: OSI Approved :: MIT License
Classifier: Operating System :: OS Independent
Requires-Python: >=3.8
License-File: LICENSE
